datasette_enrichments_gmap_geocode/__init__.py
datasette_enrichments_gmap_geocode-0.1.3.dist-info/LICENSE
datasette_enrichments_gmap_geocode-0.1.3.dist-info/METADATA
datasette_enrichments_gmap_geocode-0.1.3.dist-info/WHEEL
datasette_enrichments_gmap_geocode-0.1.3.dist-info/entry_points.txt
datasette_enrichments_gmap_geocode-0.1.3.dist-info/top_level.txt
datasette_enrichments_gmap_geocode-0.1.3.dist-info/RECORD
