Metadata-Version: 2.1
Name: datasette-enrichments-gmap-geocode
Version: 0.1.3
Summary: Geocoding enrichment using Google Maps API
Author: Hamilton Carter
License: Apache-2.0
Project-URL: Homepage, https://github.com/datasette/datasette-enrichments-gmap-geocode
Project-URL: Changelog, https://github.com/datasette/datasette-enrichments-gmap-geocode/releases
Project-URL: Issues, https://github.com/datasette/datasette-enrichments-gmap-geocode/issues
Project-URL: CI, https://github.com/datasette/datasette-enrichments-gmap-geocode/actions
Classifier: Framework :: Datasette
Classifier: License :: OSI Approved :: Apache Software License
Requires-Python: >=3.8
License-File: LICENSE
Requires-Dist: datasette
Requires-Dist: datasette-enrichments >=0.2
Requires-Dist: sqlite-utils
Provides-Extra: test
Requires-Dist: pytest <=7.4.3 ; extra == 'test'
Requires-Dist: pytest-asyncio <=0.21.1 ; extra == 'test'
Requires-Dist: pytest-httpx ; extra == 'test'
